ml_solution/__init__.py
ml_solution/__version__.py
ml_solution/config.py
ml_solution/data_utils.py
ml_solution/explorer.py
ml_solution/review.py
ml_solution/dl_tools/__init__.py
ml_solution/dl_tools/dl_dataset.py
ml_solution/dl_tools/engine.py
ml_solution/dl_tools/engine_utils.py
ml_solution/dl_tools/lego.py
ml_solution/dl_tools/train_utils.py
ml_solution/dl_tools/visual_aug.py
ml_solution/dl_tools/models/__init__.py
ml_solution/dl_tools/models/beit3.py
ml_solution/dl_tools/models/beit3_utils.py
ml_solution/dl_tools/models/bert.py
ml_solution-0.0.3.dist-info/METADATA
ml_solution-0.0.3.dist-info/WHEEL
ml_solution-0.0.3.dist-info/top_level.txt
ml_solution-0.0.3.dist-info/RECORD
