Metadata-Version: 2.1
Name: ml-solution
Version: 0.0.3
Summary: A mechine learning pipeline lib.
Home-page: https://github.com/JiahongZhang/ml_solution
Author: hugo
Author-email: hugo279@foxmail.com
Classifier: Development Status :: 3 - Alpha
Classifier: Programming Language :: Python :: 3
Classifier: License :: OSI Approved :: MIT License
Classifier: Operating System :: OS Independent
Requires-Python: >=3.10
Requires-Dist: pandas (>=2.0)
Requires-Dist: torch (>=1.12)
Requires-Dist: seaborn (>=0.13)
Requires-Dist: timm (>=0.6)
Requires-Dist: opencv-python (>=4.8)
Requires-Dist: transformers (>=4.36)
Requires-Dist: torchscale (>=0.3)
Requires-Dist: scikit-learn (>=1.3)
Requires-Dist: wandb (>=0.16)
Requires-Dist: sentencepiece (>=0.1.99)
